medical_image/__init__.py
medical_image/generate_dcm.py
medical_image/utils.py
medical_image/fonts/NotoSansCJKkr-Bold.otf
medical_image/fonts/NotoSansCJKkr-DemiLight.otf
medical_image/fonts/NotoSansCJKkr-Medium.otf
medical_image/fonts/NotoSansCJKkr-Thin.otf
medical_image/logo/colorbar.png
medical_image/logo/deepnoid.png
medical_image/logo/deepnoid_bold.png
medical_image/tests/test_sc.py
medical_image/tests/test_type.py
medical_image-0.0.56.dist-info/METADATA
medical_image-0.0.56.dist-info/WHEEL
medical_image-0.0.56.dist-info/top_level.txt
medical_image-0.0.56.dist-info/RECORD
