Metadata-Version: 2.1
Name: medical-image
Version: 0.0.56
Summary: DICOM Processing Library for AI Apps
Home-page: https://www.deepnoid.com
Author: Hwa Pyung Kim
Author-email: hpkim0512@deepnoid.com
License: MIT
Requires-Python: >=3
Requires-Dist: opencv-python (==4.3.0.38)
Requires-Dist: opencv-python-headless (==4.3.0.38)
Requires-Dist: pydicom (==2.1.2)
Requires-Dist: numpy (==1.19.5)
Requires-Dist: pillow
